Metadata-Version: 2.4
Name: fvs-python
Version: 0.2.3
Summary: Python implementation of the Forest Vegetation Simulator - Part of the FIA Python Ecosystem
Author-email: Chris Mihiar <chris.mihiar@gmail.com>
Maintainer-email: Chris Mihiar <chris.mihiar@gmail.com>
License: MIT
Project-URL: Homepage, https://fiatools.org/tools/pyfvs/
Project-URL: Repository, https://github.com/mihiarc/pyfvs
Project-URL: Documentation, https://mihiarc.github.io/pyfvs/
Project-URL: Source Code, https://github.com/mihiarc/pyfvs
Project-URL: Bug Tracker, https://github.com/mihiarc/pyfvs/issues
Project-URL: Changelog, https://github.com/mihiarc/pyfvs/releases
Project-URL: FIA Ecosystem, https://fiatools.org
Keywords: fvs,forest-vegetation-simulator,growth-simulation,yield-tables,forestry,southern-pine,loblolly-pine,longleaf-pine,slash-pine,shortleaf-pine,chapman-richards,individual-tree-growth,stand-projection,timber-volume,fia,fiatools,forest-inventory,usda,forest-service
Classifier: Development Status :: 4 - Beta
Classifier: Intended Audience :: Science/Research
Classifier: Intended Audience :: Developers
Classifier: Topic :: Scientific/Engineering
Classifier: Topic :: Scientific/Engineering :: Bio-Informatics
Classifier: Topic :: Scientific/Engineering :: Information Analysis
Classifier: License :: OSI Approved :: MIT License
Classifier: Operating System :: OS Independent
Classifier: Natural Language :: English
Classifier: Environment :: Console
Classifier: Programming Language :: Python :: 3
Classifier: Programming Language :: Python :: 3.9
Classifier: Programming Language :: Python :: 3.10
Classifier: Programming Language :: Python :: 3.11
Classifier: Programming Language :: Python :: 3.12
Requires-Python: >=3.8
License-File: LICENSE
Requires-Dist: numpy>=1.21.0
Requires-Dist: pandas>=1.3.0
Requires-Dist: scipy>=1.7.0
Requires-Dist: matplotlib>=3.4.0
Requires-Dist: seaborn>=0.11.0
Requires-Dist: pyyaml>=6.0.0
Requires-Dist: pydantic>=2.5.0
Requires-Dist: tomli>=2.0.0; python_version < "3.11"
Requires-Dist: tomli-w>=1.0.0
Requires-Dist: tabulate>=0.9.0
Requires-Dist: openpyxl>=3.0.0
Requires-Dist: rich>=12.0.0
Provides-Extra: dev
Requires-Dist: pytest>=6.0.0; extra == "dev"
Requires-Dist: pytest-cov>=3.0.0; extra == "dev"
Requires-Dist: black>=22.0.0; extra == "dev"
Requires-Dist: flake8>=4.0.0; extra == "dev"
Requires-Dist: mypy>=0.900; extra == "dev"
Requires-Dist: pre-commit>=2.15.0; extra == "dev"
Requires-Dist: mkdocs>=1.6.0; extra == "dev"
Requires-Dist: mkdocs-material>=9.5.0; extra == "dev"
Requires-Dist: mkdocstrings[python]>=0.24.0; extra == "dev"
Provides-Extra: test
Requires-Dist: pytest>=6.0.0; extra == "test"
Requires-Dist: pytest-cov>=3.0.0; extra == "test"
Requires-Dist: pytest-xdist>=2.0.0; extra == "test"
Provides-Extra: docs
Requires-Dist: mkdocs>=1.6.0; extra == "docs"
Requires-Dist: mkdocs-material>=9.5.0; extra == "docs"
Requires-Dist: mkdocstrings[python]>=0.24.0; extra == "docs"
Requires-Dist: pymdown-extensions>=10.7; extra == "docs"
Dynamic: license-file
